pytest_unhandled_exception_exit_code.py
pytest_unhandled_exception_exit_code-0.0.2.dist-info/LICENSE
pytest_unhandled_exception_exit_code-0.0.2.dist-info/METADATA
pytest_unhandled_exception_exit_code-0.0.2.dist-info/WHEEL
pytest_unhandled_exception_exit_code-0.0.2.dist-info/entry_points.txt
pytest_unhandled_exception_exit_code-0.0.2.dist-info/top_level.txt
pytest_unhandled_exception_exit_code-0.0.2.dist-info/RECORD
