Metadata-Version: 2.1
Name: pytest-unhandled-exception-exit-code
Version: 0.0.2
Summary: Plugin for py.test set a different exit code on uncaught exceptions
Home-page: https://github.com/bra-fsn/pytest-unhandled-exception-exit-code
Author: NAGY, Attila
Author-email: nagy.attila+pytest@gmail.com
License: BSD
Keywords: pytest,py.test
Platform: UNKNOWN
Classifier: Development Status :: 5 - Production/Stable
Classifier: Intended Audience :: Developers
Classifier: License :: OSI Approved :: MIT License
Classifier: Programming Language :: Python :: 2
Classifier: Programming Language :: Python :: 3
Classifier: Framework :: Pytest
Requires-Dist: pytest (>=2.3)
